Minesweeper/__init__.py
Minesweeper/board.py
Minesweeper/cell.py
Minesweeper/exceptions/__init__.py
Minesweeper/exceptions/exceptions.py
Minesweeper/utils/__init__.py
Minesweeper/utils/utils.py
SweeperPy-0.0.1.dist-info/LICENSE
SweeperPy-0.0.1.dist-info/METADATA
SweeperPy-0.0.1.dist-info/WHEEL
SweeperPy-0.0.1.dist-info/top_level.txt
SweeperPy-0.0.1.dist-info/RECORD
