Metadata-Version: 2.1
Name: SweeperPy
Version: 0.0.1
Summary: A Library to make simple minesweeper games using OOP
Author-email: Ousama Alhennawi <osamaziadalhinawi@gmail.com>
License: MIT License        
Project-URL: Homepage, https://github.com/osam7a/Minesweeper
Classifier: Programming Language :: Python :: 3
Classifier: License :: OSI Approved :: MIT License
Classifier: Operating System :: OS Independent
Requires-Python: >=3.7
License-File: LICENSE
